<thlogic>
  <attr sel="#mainMenu"
        th:fragment="mainMenuFragment"
        th:with="shopMapping = ${T(com.tbar.makeupstoreapplication.utility.AppMappings).SHOP},
                    product_type = ${T(com.tbar.makeupstoreapplication.utility.AppMappings).QUERY_PARAM_PRODUCT_TYPE}"/>

  <attr sel="#appTitle"
        th:text="${@environment.getProperty('applicationTitle')}"/>

  <attr sel="#homeLink"
        th:href="@{__${T(com.tbar.makeupstoreapplication.utility.AppMappings).HOME}__}"
        th:text="#{home.name}"/>

  <attr sel="#shopLink"
        th:href="@{/__${T(com.tbar.makeupstoreapplication.utility.AppMappings).SHOP}__}"
        th:text="#{shop.name}"/>
  <attr sel="#faceLink"
        th:href="@{/__${shopMapping}__(__${product_type}__ = foundation)}"
        th:text="#{face.name}"/>
  <attr sel="#eyesLink"
        th:href="@{/__${shopMapping}__(__${product_type}__ = eyeshadow)}"
        th:text="#{eyes.name}"/>
  <attr sel="#lipsLink"
        th:href="@{/__${shopMapping}__(__${product_type}__ = lipstick)}"
        th:text="#{lips.name}"/>
  <attr sel="#nailsLink"
        th:href="@{/__${shopMapping}__(__${product_type}__ = nail_polish)}"
        th:text="#{nails.name}"/>

  <attr sel="#contactLink"
        th:href="@{/__${T(com.tbar.makeupstoreapplication.utility.AppMappings).CONTACT}__}"
        th:text="#{contact.name}"/>

  <attr sel="#localeSwitcherOption"
        th:with="currentLocale = ${__${T(com.tbar.makeupstoreapplication.utility.AttributeNames).CURRENT_LANGUAGE}__}"
        th:each="language : ${#strings.listSplit(@environment.getProperty('applicationLanguagesList'), ',')}"
        th:text="${#strings.toUpperCase(language)}"
        th:value="${language}"
        th:selected="${#strings.equals(language, currentLocale)}"/>

</thlogic>